Workbook

Sheet Dashboard
A1: Metric | B1: Value
A2: Total Sales Today | B2: =SUMIFS('Orders & Payments'!$I:$I,'Orders & Payments'!$A:$A,TODAY()) -> 0
A3: Total Sales This Month | B3: =SUMIFS('Orders & Payments'!$I:$I,'Orders & Payments'!$A:$A,">="&EOMONTH(TODAY(),-1)+1,'Orders & Payments'!$A:$A,"<="&EOMONTH(TODAY(),0)) -> 0
A4: Cash Sales Today | B4: =SUMIFS('Orders & Payments'!$I:$I,'Orders & Payments'!$A:$A,TODAY(),'Orders & Payments'!$H:$H,"Cash") -> 0
A5: Bank & MoMo Sales Today | B5: =SUMIFS('Orders & Payments'!$I:$I,'Orders & Payments'!$A:$A,TODAY(),'Orders & Payments'!$H:$H,"National Bank")+SUMIFS('Orders & Payments'!$I:$I,'Orders & Payments'!$A:$A,TODAY(),'Orders & Payments'!$H:$H,"Standard Bank")+SUMIFS('Orders & Payments'!$I:$I,'Orders & Payments'!$A:$A,TODAY(),'Orders & Payments'!$H:$H,"Airtel Money")+SUMIFS('Orders & Payments'!$I:$I,'Orders & Payments'!$A:$A,TODAY(),'Orders & Payments'!$H:$H,"Mpamba") -> 0

Sheet Orders & Payments
A1: Date | B1: Order ID | C1: Customer Name | D1: Type of Arrangement | E1: No. of Arrangements | F1: Flower Types Used | G1: Total Qty Used | H1: Payment Method | I1: Amount | J1: Payment Ref/Txn ID | K1: Remarks

Sheet Stock Received
A1: Date | B1: Source | C1: Type (Flower/Ribbon/etc.) | D1: Specific Item | E1: Color | F1: Qty Received | G1: Cost per Unit | H1: Total Cost | I1: Received By | J1: Remarks
H2: =F2*G2 -> 0

Sheet Stock Tracker
A1: Item | B1: Type | C1: Color | D1: Opening Stock | E1: Received | F1: Used in Arrangements | G1: Losses | H1: Closing Balance
E2: =IFERROR(SUMIFS('Stock Received'!$F:$F,'Stock Received'!$D:$D,$A2,'Stock Received'!$E:$E,$C2),0) -> 0 | F2: =IFERROR(SUMIFS('Arrangement Tracker'!$F:$F,'Arrangement Tracker'!$D:$D,$A2,'Arrangement Tracker'!$E:$E,$C2),0) -> 0 | G2: =IFERROR(SUMIFS('Losses & Damages'!$E:$E,'Losses & Damages'!$C:$C,$A2,'Losses & Damages'!$D:$D,$C2),0) -> 0 | H2: =IFERROR(D2+E2-F2-G2,0) -> 0
E3: =IFERROR(SUMIFS('Stock Received'!$F:$F,'Stock Received'!$D:$D,$A3,'Stock Received'!$E:$E,$C3),0) -> 0 | F3: =IFERROR(SUMIFS('Arrangement Tracker'!$F:$F,'Arrangement Tracker'!$D:$D,$A3,'Arrangement Tracker'!$E:$E,$C3),0) -> 0 | G3: =IFERROR(SUMIFS('Losses & Damages'!$E:$E,'Losses & Damages'!$C:$C,$A3,'Losses & Damages'!$D:$D,$C3),0) -> 0 | H3: =IFERROR(D3+E3-F3-G3,0) -> 0
E4: =IFERROR(SUMIFS('Stock Received'!$F:$F,'Stock Received'!$D:$D,$A4,'Stock Received'!$E:$E,$C4),0) -> 0 | F4: =IFERROR(SUMIFS('Arrangement Tracker'!$F:$F,'Arrangement Tracker'!$D:$D,$A4,'Arrangement Tracker'!$E:$E,$C4),0) -> 0 | G4: =IFERROR(SUMIFS('Losses & Damages'!$E:$E,'Losses & Damages'!$C:$C,$A4,'Losses & Damages'!$D:$D,$C4),0) -> 0 | H4: =IFERROR(D4+E4-F4-G4,0) -> 0
E5: =IFERROR(SUMIFS('Stock Received'!$F:$F,'Stock Received'!$D:$D,$A5,'Stock Received'!$E:$E,$C5),0) -> 0 | F5: =IFERROR(SUMIFS('Arrangement Tracker'!$F:$F,'Arrangement Tracker'!$D:$D,$A5,'Arrangement Tracker'!$E:$E,$C5),0) -> 0 | G5: =IFERROR(SUMIFS('Losses & Damages'!$E:$E,'Losses & Damages'!$C:$C,$A5,'Losses & Damages'!$D:$D,$C5),0) -> 0 | H5: =IFERROR(D5+E5-F5-G5,0) -> 0
E6: =IFERROR(SUMIFS('Stock Received'!$F:$F,'Stock Received'!$D:$D,$A6,'Stock Received'!$E:$E,$C6),0) -> 0 | F6: =IFERROR(SUMIFS('Arrangement Tracker'!$F:$F,'Arrangement Tracker'!$D:$D,$A6,'Arrangement Tracker'!$E:$E,$C6),0) -> 0 | G6: =IFERROR(SUMIFS('Losses & Damages'!$E:$E,'Losses & Damages'!$C:$C,$A6,'Losses & Damages'!$D:$D,$C6),0) -> 0 | H6: =IFERROR(D6+E6-F6-G6,0) -> 0
E7: =IFERROR(SUMIFS('Stock Received'!$F:$F,'Stock Received'!$D:$D,$A7,'Stock Received'!$E:$E,$C7),0) -> 0 | F7: =IFERROR(SUMIFS('Arrangement Tracker'!$F:$F,'Arrangement Tracker'!$D:$D,$A7,'Arrangement Tracker'!$E:$E,$C7),0) -> 0 | G7: =IFERROR(SUMIFS('Losses & Damages'!$E:$E,'Losses & Damages'!$C:$C,$A7,'Losses & Damages'!$D:$D,$C7),0) -> 0 | H7: =IFERROR(D7+E7-F7-G7,0) -> 0
E8: =IFERROR(SUMIFS('Stock Received'!$F:$F,'Stock Received'!$D:$D,$A8,'Stock Received'!$E:$E,$C8),0) -> 0 | F8: =IFERROR(SUMIFS('Arrangement Tracker'!$F:$F,'Arrangement Tracker'!$D:$D,$A8,'Arrangement Tracker'!$E:$E,$C8),0) -> 0 | G8: =IFERROR(SUMIFS('Losses & Damages'!$E:$E,'Losses & Damages'!$C:$C,$A8,'Losses & Damages'!$D:$D,$C8),0) -> 0 | H8: =IFERROR(D8+E8-F8-G8,0) -> 0
E9: =IFERROR(SUMIFS('Stock Received'!$F:$F,'Stock Received'!$D:$D,$A9,'Stock Received'!$E:$E,$C9),0) -> 0 | F9: =IFERROR(SUMIFS('Arrangement Tracker'!$F:$F,'Arrangement Tracker'!$D:$D,$A9,'Arrangement Tracker'!$E:$E,$C9),0) -> 0 | G9: =IFERROR(SUMIFS('Losses & Damages'!$E:$E,'Losses & Damages'!$C:$C,$A9,'Losses & Damages'!$D:$D,$C9),0) -> 0 | H9: =IFERROR(D9+E9-F9-G9,0) -> 0
E10: =IFERROR(SUMIFS('Stock Received'!$F:$F,'Stock Received'!$D:$D,$A10,'Stock Received'!$E:$E,$C10),0) -> 0 | F10: =IFERROR(SUMIFS('Arrangement Tracker'!$F:$F,'Arrangement Tracker'!$D:$D,$A10,'Arrangement Tracker'!$E:$E,$C10),0) -> 0 | G10: =IFERROR(SUMIFS('Losses & Damages'!$E:$E,'Losses & Damages'!$C:$C,$A10,'Losses & Damages'!$D:$D,$C10),0) -> 0 | H10: =IFERROR(D10+E10-F10-G10,0) -> 0
E11: =IFERROR(SUMIFS('Stock Received'!$F:$F,'Stock Received'!$D:$D,$A11,'Stock Received'!$E:$E,$C11),0) -> 0 | F11: =IFERROR(SUMIFS('Arrangement Tracker'!$F:$F,'Arrangement Tracker'!$D:$D,$A11,'Arrangement Tracker'!$E:$E,$C11),0) -> 0 | G11: =IFERROR(SUMIFS('Losses & Damages'!$E:$E,'Losses & Damages'!$C:$C,$A11,'Losses & Damages'!$D:$D,$C11),0) -> 0 | H11: =IFERROR(D11+E11-F11-G11,0) -> 0
E12: =IFERROR(SUMIFS('Stock Received'!$F:$F,'Stock Received'!$D:$D,$A12,'Stock Received'!$E:$E,$C12),0) -> 0 | F12: =IFERROR(SUMIFS('Arrangement Tracker'!$F:$F,'Arrangement Tracker'!$D:$D,$A12,'Arrangement Tracker'!$E:$E,$C12),0) -> 0 | G12: =IFERROR(SUMIFS('Losses & Damages'!$E:$E,'Losses & Damages'!$C:$C,$A12,'Losses & Damages'!$D:$D,$C12),0) -> 0 | H12: =IFERROR(D12+E12-F12-G12,0) -> 0
E13: =IFERROR(SUMIFS('Stock Received'!$F:$F,'Stock Received'!$D:$D,$A13,'Stock Received'!$E:$E,$C13),0) -> 0 | F13: =IFERROR(SUMIFS('Arrangement Tracker'!$F:$F,'Arrangement Tracker'!$D:$D,$A13,'Arrangement Tracker'!$E:$E,$C13),0) -> 0 | G13: =IFERROR(SUMIFS('Losses & Damages'!$E:$E,'Losses & Damages'!$C:$C,$A13,'Losses & Damages'!$D:$D,$C13),0) -> 0 | H13: =IFERROR(D13+E13-F13-G13,0) -> 0
... E501: =IFERROR(SUMIFS('Stock Received'!$F:$F,'Stock Received'!$D:$D,$A501,'Stock Received'!$E:$E,$C501),0) -> 0 | F501: =IFERROR(SUMIFS('Arrangement Tracker'!$F:$F,'Arrangement Tracker'!$D:$D,$A501,'Arrangement Tracker'!$E:$E,$C501),0) -> 0 | G501: =IFERROR(SUMIFS('Losses & Damages'!$E:$E,'Losses & Damages'!$C:$C,$A501,'Losses & Damages'!$D:$D,$C501),0) -> 0 | H501: =IFERROR(D501+E501-F501-G501,0) -> 0

Sheet Arrangement Tracker
A1: Date | B1: Order ID | C1: Arrangement Type | D1: Flower Type | E1: Color | F1: No. of Stems Used | G1: Ribbon Type | H1: Ribbon Color | I1: Other Items Used

Sheet Losses & Damages
A1: Date | B1: Type | C1: Item | D1: Color | E1: Qty Lost | F1: Cause | G1: Action Taken | H1: Logged By

Sheet Bank & MoMo
A1: Date | B1: Order ID | C1: Amount | D1: Method | E1: Payment Ref | F1: Received By | G1: Confirmed in Bank/MoMo? | H1: Date Verified
A2: =IFERROR(INDEX('Orders & Payments'!$A$2:$A$500,MATCH($E2,'Orders & Payments'!$J$2:$J$500,0)),"") | B2: =IFERROR(INDEX('Orders & Payments'!$B$2:$B$500,MATCH($E2,'Orders & Payments'!$J$2:$J$500,0)),"") | C2: =IFERROR(INDEX('Orders & Payments'!$I$2:$I$500,MATCH($E2,'Orders & Payments'!$J$2:$J$500,0)),"") | D2: =IFERROR(INDEX('Orders & Payments'!$H$2:$H$500,MATCH($E2,'Orders & Payments'!$J$2:$J$500,0)),"")
A3: =IFERROR(INDEX('Orders & Payments'!$A$2:$A$500,MATCH($E3,'Orders & Payments'!$J$2:$J$500,0)),"") | B3: =IFERROR(INDEX('Orders & Payments'!$B$2:$B$500,MATCH($E3,'Orders & Payments'!$J$2:$J$500,0)),"") | C3: =IFERROR(INDEX('Orders & Payments'!$I$2:$I$500,MATCH($E3,'Orders & Payments'!$J$2:$J$500,0)),"") | D3: =IFERROR(INDEX('Orders & Payments'!$H$2:$H$500,MATCH($E3,'Orders & Payments'!$J$2:$J$500,0)),"")
A4: =IFERROR(INDEX('Orders & Payments'!$A$2:$A$500,MATCH($E4,'Orders & Payments'!$J$2:$J$500,0)),"") | B4: =IFERROR(INDEX('Orders & Payments'!$B$2:$B$500,MATCH($E4,'Orders & Payments'!$J$2:$J$500,0)),"") | C4: =IFERROR(INDEX('Orders & Payments'!$I$2:$I$500,MATCH($E4,'Orders & Payments'!$J$2:$J$500,0)),"") | D4: =IFERROR(INDEX('Orders & Payments'!$H$2:$H$500,MATCH($E4,'Orders & Payments'!$J$2:$J$500,0)),"")
A5: =IFERROR(INDEX('Orders & Payments'!$A$2:$A$500,MATCH($E5,'Orders & Payments'!$J$2:$J$500,0)),"") | B5: =IFERROR(INDEX('Orders & Payments'!$B$2:$B$500,MATCH($E5,'Orders & Payments'!$J$2:$J$500,0)),"") | C5: =IFERROR(INDEX('Orders & Payments'!$I$2:$I$500,MATCH($E5,'Orders & Payments'!$J$2:$J$500,0)),"") | D5: =IFERROR(INDEX('Orders & Payments'!$H$2:$H$500,MATCH($E5,'Orders & Payments'!$J$2:$J$500,0)),"")
A6: =IFERROR(INDEX('Orders & Payments'!$A$2:$A$500,MATCH($E6,'Orders & Payments'!$J$2:$J$500,0)),"") | B6: =IFERROR(INDEX('Orders & Payments'!$B$2:$B$500,MATCH($E6,'Orders & Payments'!$J$2:$J$500,0)),"") | C6: =IFERROR(INDEX('Orders & Payments'!$I$2:$I$500,MATCH($E6,'Orders & Payments'!$J$2:$J$500,0)),"") | D6: =IFERROR(INDEX('Orders & Payments'!$H$2:$H$500,MATCH($E6,'Orders & Payments'!$J$2:$J$500,0)),"")
A7: =IFERROR(INDEX('Orders & Payments'!$A$2:$A$500,MATCH($E7,'Orders & Payments'!$J$2:$J$500,0)),"") | B7: =IFERROR(INDEX('Orders & Payments'!$B$2:$B$500,MATCH($E7,'Orders & Payments'!$J$2:$J$500,0)),"") | C7: =IFERROR(INDEX('Orders & Payments'!$I$2:$I$500,MATCH($E7,'Orders & Payments'!$J$2:$J$500,0)),"") | D7: =IFERROR(INDEX('Orders & Payments'!$H$2:$H$500,MATCH($E7,'Orders & Payments'!$J$2:$J$500,0)),"")
A8: =IFERROR(INDEX('Orders & Payments'!$A$2:$A$500,MATCH($E8,'Orders & Payments'!$J$2:$J$500,0)),"") | B8: =IFERROR(INDEX('Orders & Payments'!$B$2:$B$500,MATCH($E8,'Orders & Payments'!$J$2:$J$500,0)),"") | C8: =IFERROR(INDEX('Orders & Payments'!$I$2:$I$500,MATCH($E8,'Orders & Payments'!$J$2:$J$500,0)),"") | D8: =IFERROR(INDEX('Orders & Payments'!$H$2:$H$500,MATCH($E8,'Orders & Payments'!$J$2:$J$500,0)),"")
A9: =IFERROR(INDEX('Orders & Payments'!$A$2:$A$500,MATCH($E9,'Orders & Payments'!$J$2:$J$500,0)),"") | B9: =IFERROR(INDEX('Orders & Payments'!$B$2:$B$500,MATCH($E9,'Orders & Payments'!$J$2:$J$500,0)),"") | C9: =IFERROR(INDEX('Orders & Payments'!$I$2:$I$500,MATCH($E9,'Orders & Payments'!$J$2:$J$500,0)),"") | D9: =IFERROR(INDEX('Orders & Payments'!$H$2:$H$500,MATCH($E9,'Orders & Payments'!$J$2:$J$500,0)),"")
A10: =IFERROR(INDEX('Orders & Payments'!$A$2:$A$500,MATCH($E10,'Orders & Payments'!$J$2:$J$500,0)),"") | B10: =IFERROR(INDEX('Orders & Payments'!$B$2:$B$500,MATCH($E10,'Orders & Payments'!$J$2:$J$500,0)),"") | C10: =IFERROR(INDEX('Orders & Payments'!$I$2:$I$500,MATCH($E10,'Orders & Payments'!$J$2:$J$500,0)),"") | D10: =IFERROR(INDEX('Orders & Payments'!$H$2:$H$500,MATCH($E10,'Orders & Payments'!$J$2:$J$500,0)),"")
A11: =IFERROR(INDEX('Orders & Payments'!$A$2:$A$500,MATCH($E11,'Orders & Payments'!$J$2:$J$500,0)),"") | B11: =IFERROR(INDEX('Orders & Payments'!$B$2:$B$500,MATCH($E11,'Orders & Payments'!$J$2:$J$500,0)),"") | C11: =IFERROR(INDEX('Orders & Payments'!$I$2:$I$500,MATCH($E11,'Orders & Payments'!$J$2:$J$500,0)),"") | D11: =IFERROR(INDEX('Orders & Payments'!$H$2:$H$500,MATCH($E11,'Orders & Payments'!$J$2:$J$500,0)),"")
A12: =IFERROR(INDEX('Orders & Payments'!$A$2:$A$500,MATCH($E12,'Orders & Payments'!$J$2:$J$500,0)),"") | B12: =IFERROR(INDEX('Orders & Payments'!$B$2:$B$500,MATCH($E12,'Orders & Payments'!$J$2:$J$500,0)),"") | C12: =IFERROR(INDEX('Orders & Payments'!$I$2:$I$500,MATCH($E12,'Orders & Payments'!$J$2:$J$500,0)),"") | D12: =IFERROR(INDEX('Orders & Payments'!$H$2:$H$500,MATCH($E12,'Orders & Payments'!$J$2:$J$500,0)),"")
A13: =IFERROR(INDEX('Orders & Payments'!$A$2:$A$500,MATCH($E13,'Orders & Payments'!$J$2:$J$500,0)),"") | B13: =IFERROR(INDEX('Orders & Payments'!$B$2:$B$500,MATCH($E13,'Orders & Payments'!$J$2:$J$500,0)),"") | C13: =IFERROR(INDEX('Orders & Payments'!$I$2:$I$500,MATCH($E13,'Orders & Payments'!$J$2:$J$500,0)),"") | D13: =IFERROR(INDEX('Orders & Payments'!$H$2:$H$500,MATCH($E13,'Orders & Payments'!$J$2:$J$500,0)),"")
... A501: =IFERROR(INDEX('Orders & Payments'!$A$2:$A$500,MATCH($E501,'Orders & Payments'!$J$2:$J$500,0)),"") | B501: =IFERROR(INDEX('Orders & Payments'!$B$2:$B$500,MATCH($E501,'Orders & Payments'!$J$2:$J$500,0)),"") | C501: =IFERROR(INDEX('Orders & Payments'!$I$2:$I$500,MATCH($E501,'Orders & Payments'!$J$2:$J$500,0)),"") | D501: =IFERROR(INDEX('Orders & Payments'!$H$2:$H$500,MATCH($E501,'Orders & Payments'!$J$2:$J$500,0)),"")

Sheet Reference Lists
A1: Flower Types | B1: Ribbon Colors | C1: Cellophane Colors | D1: Payment Methods | E1: Arrangement Types
A2: High Society | B2: Royal Blue | C2: Clear | D2: Cash | E2: Bouquet
A3: First Red | B3: Turquoise | C3: Black | D3: National Bank | E3: Vase arrangement
A4: White Acetal | B4: Hot Pink | C4: Gold | D4: Standard Bank | E4: Box arrangement
A5: Red Grand Gala | B5: Baby Pink | C5: Yellow | D5: Airtel Money | E5: Wreath
A6: Lambada | B6: Red | C6: Cream | D6: Mpamba | E6: Casket spray
A7: Ensemble | B7: Yellow | C7: Red | E7: Table arrangement
A8: Hot Pink | B8: Green | C8: Green
A9: Starlight | B9: Purple | C9: Blue
A10: White Hybrid | B10: White | C10: Purple
A11: Mint Hybrid | B11: Black | C11: Pink
A12: Spray rose | B12: Silver | C12: Silver
A13: Solidago | B13: Gold | C13: Orange
A14: Asthers White | B14: Orange | C14: Maroon
A15: Asthers Pink | B15: Maroon
A16: Asthers Purple | B16: Light Pink
A17: Asthers Lilac | B17: Dark Pink
A18: Yarrow White | B18: Light Green
A19: Yarrow Pink | B19: Dark Green
A20: Daniella | B20: Light Blue
A21: Chrysanths | B21: Dark Blue
A22: King Protea
A23: Saffari Sunset
A24: Warrato
A25: Yellow Protea
A26: Hi-Gold Protea
A27: Baby's Breath
A28: Sunflowers
A29: Alstomeria
A30: Statice White
A31: Statice Yellow
A32: Statice Peach
A33: Statice Blue
... A38: Yarrow
